brasilapi/__init__.py
brasilapi/client.py
brasilapi/dto/bank.py
brasilapi/dto/cep.py
brasilapi/dto/ddd.py
brasilapi/dto/feriado.py
brasilapi/dto/fipe.py
brasilapi/exception/__init__.py
brasilapi/exception/request_exception.py
brasilapi/exception/validation_exception.py
brasilapi/http/__init__.py
brasilapi/http/aiohttp_client.py
brasilapi/services/bank.py
brasilapi/services/base.py
brasilapi/services/cep.py
brasilapi/services/ddd.py
brasilapi/services/feriado.py
brasilapi/services/fipe.py
brasilapi-0.1.0.dist-info/LICENSE
brasilapi-0.1.0.dist-info/METADATA
brasilapi-0.1.0.dist-info/WHEEL
brasilapi-0.1.0.dist-info/RECORD
