Metadata-Version: 2.1
Name: brasilapi
Version: 0.1.0
Summary: Python async client for BrasilAPI
Home-page: https://github.com/paulovitorweb/brasilapi-python
License: MIT
Keywords: brasilapi,http,asyncio
Author: Paulo Freitas
Author-email: paulogeo5@gmail.com
Requires-Python: >=3.11,<4.0
Classifier: Framework :: AsyncIO
Classifier: Framework :: Pydantic :: 2
Classifier: Framework :: aiohttp
Classifier: License :: OSI Approved :: MIT License
Classifier: Programming Language :: Python :: 3
Classifier: Programming Language :: Python :: 3.11
Classifier: Topic :: Internet :: WWW/HTTP
Classifier: Topic :: Software Development :: Libraries
Classifier: Topic :: Utilities
Requires-Dist: aiohttp (>=3.8.6,<4.0.0)
Requires-Dist: pydantic (>=2.4.2,<3.0.0)
Project-URL: Documentation, https://github.com/paulovitorweb/brasilapi-python
Project-URL: Repository, https://github.com/paulovitorweb/brasilapi-python
